<?xml version="1.0" encoding="UTF-8"?>
<DataRoot>
  <Result>
    <Code>0</Code>
    <Message/>
  </Result>
  <ApplData>
    <LawId>325AC1000000202</LawId>
    <LawNum/>
    <Article>22_2</Article>
    <Paragraph/>
    <AppdxTable/>
    <LawContents>
      <Article Num="22_2">
        <ArticleCaption>（定期講習）</ArticleCaption>
        <ArticleTitle>第二十二条の二</ArticleTitle>
        <Paragraph Num="1">
          <ParagraphNum/>
          <ParagraphSentence>
            <Sentence Num="1" WritingMode="vertical">次の各号に掲げる建築士は、三年以上五年以内において国土交通省令で定める期間ごとに、次条第一項の規定及び同条第二項において準用する第十条の二十三から第十条の二十五までの規定の定めるところにより国土交通大臣の登録を受けた者（次条において「登録講習機関」という。）が行う当該各号に定める講習を受けなければならない。</Sentence>
          </ParagraphSentence>
          <Item Num="1">
            <ItemTitle>一</ItemTitle>
            <ItemSentence>
              <Column Num="1">
                <Sentence Num="1" WritingMode="vertical">一級建築士（第二十三条第一項の建築士事務所に属するものに限る。）</Sentence>
              </Column>
              <Column Num="2">
                <Sentence Num="1" WritingMode="vertical">別表第二（一）の項講習の欄に掲げる講習</Sentence>
              </Column>
            </ItemSentence>
          </Item>
          <Item Num="2">
            <ItemTitle>二</ItemTitle>
            <ItemSentence>
              <Column Num="1">
                <Sentence Num="1" WritingMode="vertical">二級建築士（第二十三条第一項の建築士事務所に属するものに限る。）</Sentence>
              </Column>
              <Column Num="2">
                <Sentence Num="1" WritingMode="vertical">別表第二（二）の項講習の欄に掲げる講習</Sentence>
              </Column>
            </ItemSentence>
          </Item>
          <Item Num="3">
            <ItemTitle>三</ItemTitle>
            <ItemSentence>
              <Column Num="1">
                <Sentence Num="1" WritingMode="vertical">木造建築士（第二十三条第一項の建築士事務所に属するものに限る。）</Sentence>
              </Column>
              <Column Num="2">
                <Sentence Num="1" WritingMode="vertical">別表第二（三）の項講習の欄に掲げる講習</Sentence>
              </Column>
            </ItemSentence>
          </Item>
          <Item Num="4">
            <ItemTitle>四</ItemTitle>
            <ItemSentence>
              <Column Num="1">
                <Sentence Num="1" WritingMode="vertical">構造設計一級建築士</Sentence>
              </Column>
              <Column Num="2">
                <Sentence Num="1" WritingMode="vertical">別表第二（四）の項講習の欄に掲げる講習</Sentence>
              </Column>
            </ItemSentence>
          </Item>
          <Item Num="5">
            <ItemTitle>五</ItemTitle>
            <ItemSentence>
              <Column Num="1">
                <Sentence Num="1" WritingMode="vertical">設備設計一級建築士</Sentence>
              </Column>
              <Column Num="2">
                <Sentence Num="1" WritingMode="vertical">別表第二（五）の項講習の欄に掲げる講習</Sentence>
              </Column>
            </ItemSentence>
          </Item>
        </Paragraph>
      </Article>
    </LawContents>
  </ApplData>
</DataRoot>
