<?xml version="1.0" encoding="UTF-8"?>
<DataRoot>
  <Result>
    <Code>0</Code>
    <Message/>
  </Result>
  <ApplData>
    <LawId>325AC0000000201</LawId>
    <LawNum/>
    <Article>7_3</Article>
    <Paragraph/>
    <AppdxTable/>
    <LawContents>
      <Article Num="7_3">
        <ArticleCaption>（建築物に関する中間検査）</ArticleCaption>
        <ArticleTitle>第七条の三</ArticleTitle>
        <Paragraph Num="1">
          <ParagraphNum/>
          <ParagraphSentence>
            <Sentence Num="1" WritingMode="vertical">建築主は、第六条第一項の規定による工事が次の各号のいずれかに該当する工程（以下「特定工程」という。）を含む場合において、当該特定工程に係る工事を終えたときは、その都度、国土交通省令で定めるところにより、建築主事等の検査を申請しなければならない。</Sentence>
          </ParagraphSentence>
          <Item Num="1">
            <ItemTitle>一</ItemTitle>
            <ItemSentence>
              <Sentence Num="1" WritingMode="vertical">階数が三以上である共同住宅の床及びはりに鉄筋を配置する工事の工程のうち政令で定める工程</Sentence>
            </ItemSentence>
          </Item>
          <Item Num="2">
            <ItemTitle>二</ItemTitle>
            <ItemSentence>
              <Sentence Num="1" WritingMode="vertical">前号に掲げるもののほか、特定行政庁が、その地方の建築物の建築の動向又は工事に関する状況その他の事情を勘案して、区域、期間又は建築物の構造、用途若しくは規模を限つて指定する工程</Sentence>
            </ItemSentence>
          </Item>
        </Paragraph>
        <Paragraph Num="2">
          <ParagraphNum>２</ParagraphNum>
          <ParagraphSentence>
            <Sentence Function="main" Num="1" WritingMode="vertical">前項の規定による申請は、特定工程に係る工事を終えた日から四日以内に建築主事等に到達するように、しなければならない。</Sentence>
            <Sentence Function="proviso" Num="2" WritingMode="vertical">ただし、申請をしなかつたことについて国土交通省令で定めるやむを得ない理由があるときは、この限りでない。</Sentence>
          </ParagraphSentence>
        </Paragraph>
        <Paragraph Num="3">
          <ParagraphNum>３</ParagraphNum>
          <ParagraphSentence>
            <Sentence Num="1" WritingMode="vertical">前項ただし書の場合における検査の申請は、その理由がやんだ日から四日以内に建築主事等に到達するように、しなければならない。</Sentence>
          </ParagraphSentence>
        </Paragraph>
        <Paragraph Num="4">
          <ParagraphNum>４</ParagraphNum>
          <ParagraphSentence>
            <Sentence Num="1" WritingMode="vertical">建築主事等が第一項の規定による申請を受理した場合においては、検査実施者は、その申請を受理した日から四日以内に、当該申請に係る工事中の建築物等（建築、大規模の修繕又は大規模の模様替の工事中の建築物及びその敷地をいう。以下この章において同じ。）について、検査前に施工された工事に係る建築物の部分及びその敷地が建築基準関係規定に適合するかどうかを検査しなければならない。</Sentence>
          </ParagraphSentence>
        </Paragraph>
        <Paragraph Num="5">
          <ParagraphNum>５</ParagraphNum>
          <ParagraphSentence>
            <Sentence Num="1" WritingMode="vertical">検査実施者は、前項の規定による検査をした場合において、工事中の建築物等が建築基準関係規定に適合することを認めたときは、国土交通省令で定めるところにより、当該建築主に対して当該特定工程に係る中間検査合格証を交付しなければならない。</Sentence>
          </ParagraphSentence>
        </Paragraph>
        <Paragraph Num="6">
          <ParagraphNum>６</ParagraphNum>
          <ParagraphSentence>
            <Sentence Num="1" WritingMode="vertical">第一項第一号の政令で定める特定工程ごとに政令で定める当該特定工程後の工程及び特定行政庁が同項第二号の指定と併せて指定する特定工程後の工程（第十八条第三十一項及び第三十五項において「特定工程後の工程」と総称する。）に係る工事は、前項の規定による当該特定工程に係る中間検査合格証の交付を受けた後でなければ、これを施工してはならない。</Sentence>
          </ParagraphSentence>
        </Paragraph>
        <Paragraph Num="7">
          <ParagraphNum>７</ParagraphNum>
          <ParagraphSentence>
            <Sentence Num="1" WritingMode="vertical">検査実施者又は前条第一項の規定による指定を受けた者は、第四項の規定による検査において建築基準関係規定に適合することを認められた工事中の建築物等について、第七条第四項、前条第一項、第四項又は次条第一項の規定による検査をするときは、第四項の規定による検査において建築基準関係規定に適合することを認められた建築物の部分及びその敷地については、これらの規定による検査をすることを要しない。</Sentence>
          </ParagraphSentence>
        </Paragraph>
        <Paragraph Num="8">
          <ParagraphNum>８</ParagraphNum>
          <ParagraphSentence>
            <Sentence Num="1" WritingMode="vertical">第一項第二号の規定による指定に関して公示その他の必要な事項は、国土交通省令で定める。</Sentence>
          </ParagraphSentence>
        </Paragraph>
      </Article>
    </LawContents>
  </ApplData>
</DataRoot>
