{
  "activeTaskId": "T725",
  "completed": 625,
  "completedQuestions": 625,
  "completed_questions": 625,
  "done": 625,
  "duplicateQualifiedReviewQuestionIdCount": 0,
  "executionStatusCounts": {
    "done": 490,
    "hold": 135,
    "pending": 309
  },
  "firestoreSourceQuestionCount": 294,
  "generatedAt": "2026-06-28T23:36:00+09:00",
  "heldQuestions": 135,
  "held_questions": 135,
  "hold": 135,
  "hold_questions": 135,
  "kouCompleted": 412,
  "kouDone": 310,
  "kouHeld": 102,
  "kouHold": 102,
  "kouPending": 0,
  "lastCompletedQuestion": "gas-shunin-otsu 2022 製造 問1",
  "lastCompletedReviewQuestionId": "ec7e5c572f2bab64",
  "lastCompletedTaskId": "T724",
  "nextActiveTaskId": "T725",
  "nextPending": "gas-shunin-otsu 2022 基礎理論 問15",
  "nextPendingPlanSequence": 733,
  "nextPendingPublicQuestionId": "d281a1bfaca91985",
  "nextPendingQualifiedReviewQuestionId": "gas-shunin-otsu:d281a1bfaca91985",
  "nextPendingQuestion": "gas-shunin-otsu 2022 基礎理論 問15",
  "nextPendingReviewId": "2022:question_2022_2:d281a1bfaca91985",
  "nextPendingTaskId": "T725",
  "otsuCompleted": 213,
  "otsuDone": 180,
  "otsuHeld": 33,
  "otsuHold": 33,
  "otsuPending": 309,
  "pending": 309,
  "pendingQuestions": 309,
  "pending_questions": 309,
  "qualificationStatusCounts": {
    "gas-shunin-kou": {
      "done": 310,
      "hold": 102
    },
    "gas-shunin-otsu": {
      "done": 180,
      "hold": 33,
      "pending": 309
    }
  },
  "reviewDecisionCounts": {
    "ok": 490,
    "hold": 135,
    "pending": 309
  },
  "total": 934,
  "totalQuestions": 934,
  "total_questions": 934,
  "updatedAt": "2026-06-29T00:07:04+09:00",
  "lastUpdatedAt": "2026-06-29T00:07:04+09:00",
  "qualificationExecutionStatusCounts": {
    "gas-shunin-kou": {
      "done": 310,
      "hold": 102
    },
    "gas-shunin-otsu": {
      "done": 180,
      "hold": 33,
      "pending": 309
    }
  }
}
