{
  "schemaVersion": "gas-shunin-law-explanation-refresh-decision/v1",
  "sequence": 232,
  "auditKey": "gas-shunin:otsu:2024:law:q03:0bc58f98058f",
  "auditInputHash": "0e250fd9e981dfb33acccfaaa12935d9a6511dda840738b1e9656ae590073baf",
  "status": "patch_applied",
  "reviewedAt": "2026-07-12T04:09:18+09:00",
  "reviewDecision": {
    "correctChoiceTextChanged": false,
    "correctChoiceTextReview": {
      "status": "confirmed",
      "flags": []
    },
    "requiresPatch": true,
    "changeFields": [
      "explanationText",
      "lawReferences",
      "lawRevisionFacts",
      "suggestedQuestions",
      "suggestedQuestionDetails"
    ],
    "proposedExplanationText": [
      "間違い。選択肢の「ガス主任技術者に対し」が誤りで、正しくは「一般ガス導管事業者に対し」である。ガス事業法第61条第2項は、技術基準に適合しないガス工作物の修理、改造、移転、使用停止又は使用制限を一般ガス導管事業者に命ずることができると定めている。",
      "間違い。選択肢の「遅滞なく」が誤りで、正しくは「事業の開始前」である。ガス事業法第64条第1項は、一般ガス導管事業者が保安規程を定め、事業の開始前に経済産業大臣へ届け出なければならないと定めている。",
      "間違い。選択肢の「公共の利益の増進を図るため」が誤りで、正しくは「ガス工作物の工事、維持及び運用に関する保安を確保するため」である。ガス事業法第64条第3項は、この保安確保のため必要があるときに保安規程の変更を命ずることができると定めている。",
      "間違い。「消費機器に関する周知及び調査の方法」は、一般ガス導管事業者の保安規程に定める事項ではない。ガス事業法施行規則第92条第1項は、保安規程の事項として、ガス工作物の工事、維持及び運用に関する組織、保安教育、巡視、点検及び検査などを定めている。消費機器の周知及び調査は、ガス事業法第159条第1項及び第2項が別途定めている。",
      "正しい。ガス事業法第62条第1項は、一般ガス導管事業者以外の者が所有又は占有するガス工作物について維持措置を講じるとき、その所有者又は占有者は措置の実施に協力するよう努めなければならないと定めている。"
    ],
    "proposedSuggestedQuestions": [
      "技術基準不適合のガス工作物に対する命令先は？",
      "保安規程はいつまでに届け出る？",
      "保安規程の変更命令ができるのはどのような場合？",
      "一般ガス導管事業者の保安規程に定める主な事項は？",
      "他者所有のガス工作物の維持措置に対する所有者の責務は？",
      "この問題の根拠条文は？"
    ],
    "proposedSuggestedQuestionDetails": [
      {
        "question": "技術基準不適合のガス工作物に対する命令先は？",
        "answer": "一般ガス導管事業者。"
      },
      {
        "question": "保安規程はいつまでに届け出る？",
        "answer": "原則として事業の開始前。"
      },
      {
        "question": "保安規程の変更命令ができるのはどのような場合？",
        "answer": "ガス工作物の工事、維持及び運用に関する保安を確保するため必要がある場合。"
      },
      {
        "question": "一般ガス導管事業者の保安規程に定める主な事項は？",
        "answer": "ガス工作物の工事、維持及び運用に関する組織、保安教育、巡視、点検、検査など。"
      },
      {
        "question": "他者所有のガス工作物の維持措置に対する所有者の責務は？",
        "answer": "措置の実施に協力するよう努める。"
      },
      {
        "question": "この問題の根拠条文は？",
        "answer": "ガス事業法第61条第2項、第62条第1項、第64条第1項・第3項及び第159条第1項・第2項並びにガス事業法施行規則第92条第1項。"
      }
    ],
    "lawRevisionFactsCorrection": {
      "basisByChoiceIndex": {
        "0": {
          "lawId": "329AC0000000051",
          "lawTitle": "ガス事業法",
          "article": "61",
          "paragraph": "2",
          "articleTextHash": "2879ed49b74edafc5ff9eb1ef65c47c39c56889676bb5af04a364664a48ebf13",
          "rawXmlHash": "31eaa1e9ee50decc15f198af778d94dd5b682db26e245afcd02a3a9e5dd58a8e"
        },
        "1": {
          "lawId": "329AC0000000051",
          "lawTitle": "ガス事業法",
          "article": "64",
          "paragraph": "1",
          "articleTextHash": "732748c9ab9f27b36c06fcd19641929eee39210fee93144422032ec706411944",
          "rawXmlHash": "b1e0502d0f76e505b935f2d020fb65fcadb2d1846e8d80e647a5d9f5db27bd0f"
        },
        "2": {
          "lawId": "329AC0000000051",
          "lawTitle": "ガス事業法",
          "article": "64",
          "paragraph": "3",
          "articleTextHash": "732748c9ab9f27b36c06fcd19641929eee39210fee93144422032ec706411944",
          "rawXmlHash": "b1e0502d0f76e505b935f2d020fb65fcadb2d1846e8d80e647a5d9f5db27bd0f"
        },
        "3": {
          "lawId": "345M50000400097",
          "lawTitle": "ガス事業法施行規則",
          "article": "92",
          "paragraph": "1",
          "articleTextHash": "81e6735d6412e972019eeff05deae87901c70944394ec1a563118d1446113d37",
          "rawXmlHash": "a28496b17ed0191c8d439753820b37d219520b24d06886118fb4d82aa9009278",
          "references": [
            {
              "lawId": "345M50000400097",
              "lawTitle": "ガス事業法施行規則",
              "article": "92",
              "paragraph": "1",
              "articleTextHash": "81e6735d6412e972019eeff05deae87901c70944394ec1a563118d1446113d37",
              "rawXmlHash": "a28496b17ed0191c8d439753820b37d219520b24d06886118fb4d82aa9009278"
            },
            {
              "lawId": "329AC0000000051",
              "lawTitle": "ガス事業法",
              "article": "159",
              "paragraph": "1",
              "articleTextHash": "709281a1c6296b238e5a757e7b318ffe6e8781bf5b69c879321c1d8942d1e0bf",
              "rawXmlHash": "c690236f0f0959bcadd8423b56fed54f9a69998e75301ab4e9cf7549c93d91fb"
            },
            {
              "lawId": "329AC0000000051",
              "lawTitle": "ガス事業法",
              "article": "159",
              "paragraph": "2",
              "articleTextHash": "709281a1c6296b238e5a757e7b318ffe6e8781bf5b69c879321c1d8942d1e0bf",
              "rawXmlHash": "c690236f0f0959bcadd8423b56fed54f9a69998e75301ab4e9cf7549c93d91fb"
            }
          ]
        },
        "4": {
          "lawId": "329AC0000000051",
          "lawTitle": "ガス事業法",
          "article": "62",
          "paragraph": "1",
          "articleTextHash": "e733c7795fcc150a4e1abdfa7020ee4c214352ba7ff42b7057f3710011bbbcb0",
          "rawXmlHash": "1ae84bb1d21aa98f8b36085fb08078e0b53597efe40989ba6432ab238a3b89a0"
        }
      }
    }
  },
  "reviewNotes": [
    "00_source.correctChoiceTextの間違い、間違い、間違い、間違い、正しいは現行法と一致する。",
    "第1肢は命令先がガス主任技術者ではなく一般ガス導管事業者、第2肢は遅滞なくではなく事業開始前、第3肢は公共の利益ではなく保安確保が正しい。",
    "第4肢の既存lawRevisionFacts主根拠は法第64条だったが、保安規程の記載事項を直接定める施行規則第92条第1項へ修正し、消費機器の周知・調査を定める法第159条第1項・第2項を補助根拠とする。",
    "正しい記述は第5肢で、answer_result_textの正解5と一致する。"
  ],
  "evidence": {
    "sourceFile": "output/gas-shunin-otsu/questions_json/2024/00_source/question_2024_1.json",
    "sourceCorrectTextUsed": true,
    "targetQuestionIds": [
      "gas-shunin-otsu-2024-law-q03-s01",
      "gas-shunin-otsu-2024-law-q03-s02",
      "gas-shunin-otsu-2024-law-q03-s03",
      "gas-shunin-otsu-2024-law-q03-s04",
      "gas-shunin-otsu-2024-law-q03-s05"
    ],
    "currentLaws": [
      {
        "lawTitle": "ガス事業法",
        "lawId": "329AC0000000051",
        "articles": [
          "61",
          "62",
          "64",
          "159"
        ],
        "sourceUrl": "https://laws.e-gov.go.jp/law/329AC0000000051"
      },
      {
        "lawTitle": "ガス事業法施行規則",
        "lawId": "345M50000400097",
        "articles": [
          "92"
        ],
        "sourceUrl": "https://laws.e-gov.go.jp/law/345M50000400097"
      }
    ],
    "referenceDate": "2026-07-12",
    "verificationStatus": "verified",
    "examTime": {
      "referenceDate": "2024",
      "verificationStatus": "source_correct_text_confirmed"
    }
  },
  "appliedAt": "2026-07-11T19:10:11Z",
  "application": {
    "patchFile": "output/gas-shunin-otsu/questions_json/2024/21_explanationText_added/question_2024_1_explanationText_added.json",
    "choiceCount": 5,
    "correctChoiceTextChanged": false
  }
}
