[
  {
    "original_question_id": "4afdf6fa51201c20",
    "public_question_id": "4afdf6fa51201c20",
    "question_url": "https://kurohon.jp/gakusei/exams_hq/hq_2/#q151",
    "questionLabel": "問151",
    "examLabel": "第2回（1994年） 午後問題",
    "source_filepath": "output/shinkyu/questions_json/1994/00_source/question_1994_7.json",
    "questionIntent": "select_correct",
    "correctChoiceText": [
      "間違い",
      "間違い",
      "間違い",
      "正しい"
    ],
    "answer_result_text": "正解は 4 です。"
  },
  {
    "original_question_id": "9f83d14c51db8736",
    "public_question_id": "9f83d14c51db8736",
    "question_url": "https://kurohon.jp/gakusei/exams_hq/hq_2/#q152",
    "questionLabel": "問152",
    "examLabel": "第2回（1994年） 午後問題",
    "source_filepath": "output/shinkyu/questions_json/1994/00_source/question_1994_7.json",
    "questionIntent": "select_correct",
    "correctChoiceText": [
      "間違い",
      "正しい",
      "間違い",
      "間違い"
    ],
    "answer_result_text": "正解は 2 です。"
  },
  {
    "original_question_id": "1d93f3b932c28fdd",
    "public_question_id": "1d93f3b932c28fdd",
    "question_url": "https://kurohon.jp/gakusei/exams_hq/hq_2/#q153",
    "questionLabel": "問153",
    "examLabel": "第2回（1994年） 午後問題",
    "source_filepath": "output/shinkyu/questions_json/1994/00_source/question_1994_7.json",
    "questionIntent": "select_incorrect",
    "correctChoiceText": [
      "正しい",
      "正しい",
      "間違い",
      "間違い"
    ],
    "answer_result_text": "正解は 3, 4 です。"
  },
  {
    "original_question_id": "3943ab502a47f955",
    "public_question_id": "3943ab502a47f955",
    "question_url": "https://kurohon.jp/gakusei/exams_hq/hq_2/#q154",
    "questionLabel": "問154",
    "examLabel": "第2回（1994年） 午後問題",
    "source_filepath": "output/shinkyu/questions_json/1994/00_source/question_1994_7.json",
    "questionIntent": "select_incorrect",
    "correctChoiceText": [
      "正しい",
      "正しい",
      "間違い",
      "正しい"
    ],
    "answer_result_text": "正解は 3 です。"
  },
  {
    "original_question_id": "166fb75047bf5ac8",
    "public_question_id": "166fb75047bf5ac8",
    "question_url": "https://kurohon.jp/gakusei/exams_hq/hq_2/#q155",
    "questionLabel": "問155",
    "examLabel": "第2回（1994年） 午後問題",
    "source_filepath": "output/shinkyu/questions_json/1994/00_source/question_1994_7.json",
    "questionIntent": "select_correct",
    "correctChoiceText": [
      "間違い",
      "正しい",
      "間違い",
      "間違い"
    ],
    "answer_result_text": "正解は 2 です。"
  },
  {
    "original_question_id": "2def622370783ac5",
    "public_question_id": "2def622370783ac5",
    "question_url": "https://kurohon.jp/gakusei/exams_hq/hq_2/#q156",
    "questionLabel": "問156",
    "examLabel": "第2回（1994年） 午後問題",
    "source_filepath": "output/shinkyu/questions_json/1994/00_source/question_1994_7.json",
    "questionIntent": "select_correct",
    "correctChoiceText": [
      "正しい",
      "間違い",
      "間違い",
      "間違い"
    ],
    "answer_result_text": "正解は 1 です。"
  },
  {
    "original_question_id": "8afbd0f0e7682da0",
    "public_question_id": "8afbd0f0e7682da0",
    "question_url": "https://kurohon.jp/gakusei/exams_hq/hq_2/#q157",
    "questionLabel": "問157",
    "examLabel": "第2回（1994年） 午後問題",
    "source_filepath": "output/shinkyu/questions_json/1994/00_source/question_1994_7.json",
    "questionIntent": "select_correct",
    "correctChoiceText": [
      "間違い",
      "間違い",
      "間違い",
      "正しい"
    ],
    "answer_result_text": "正解は 4 です。"
  },
  {
    "original_question_id": "d12408c16eee142c",
    "public_question_id": "d12408c16eee142c",
    "question_url": "https://kurohon.jp/gakusei/exams_hq/hq_2/#q158",
    "questionLabel": "問158",
    "examLabel": "第2回（1994年） 午後問題",
    "source_filepath": "output/shinkyu/questions_json/1994/00_source/question_1994_7.json",
    "questionIntent": "select_correct",
    "correctChoiceText": [
      "間違い",
      "間違い",
      "正しい",
      "間違い"
    ],
    "answer_result_text": "正解は 3 です。"
  },
  {
    "original_question_id": "dcf0ae7668d4fda8",
    "public_question_id": "dcf0ae7668d4fda8",
    "question_url": "https://kurohon.jp/gakusei/exams_hq/hq_2/#q159",
    "questionLabel": "問159",
    "examLabel": "第2回（1994年） 午後問題",
    "source_filepath": "output/shinkyu/questions_json/1994/00_source/question_1994_7.json",
    "questionIntent": "select_correct",
    "correctChoiceText": [
      "間違い",
      "間違い",
      "正しい",
      "間違い"
    ],
    "answer_result_text": "正解は 3 です。"
  },
  {
    "original_question_id": "08e2fcbd200c85f6",
    "public_question_id": "08e2fcbd200c85f6",
    "question_url": "https://kurohon.jp/gakusei/exams_hq/hq_2/#q160",
    "questionLabel": "問160",
    "examLabel": "第2回（1994年） 午後問題",
    "source_filepath": "output/shinkyu/questions_json/1994/00_source/question_1994_7.json",
    "questionIntent": "select_incorrect",
    "correctChoiceText": [
      "正しい",
      "正しい",
      "間違い",
      "正しい"
    ],
    "answer_result_text": "正解は 3 です。"
  }
]
