[
  {
    "original_question_id": "51ac04759e4afb5e",
    "public_question_id": "51ac04759e4afb5e",
    "question_url": "https://kurohon.jp/gakusei/exams_hq/hq_20/#q76",
    "questionLabel": "問76",
    "examLabel": "第20回（2012年） 午前問題",
    "source_filepath": "output/shinkyu/questions_json/2012/00_source/question_2012_4.json",
    "explanationText": [
      "正しい。アルツハイマー病では大脳皮質に老人斑を認める。",
      "間違い。ゲルストマン症候群は初期からみられる典型所見ではない。",
      "間違い。片麻痺は脳血管障害で目立つ所見で、アルツハイマー病の典型ではない。",
      "間違い。まだら認知症は脳血管性認知症で特徴的である。"
    ],
    "suggestedQuestions": [
      "アルツハイマー病の特徴はどれか"
    ],
    "suggestedQuestionDetails": [
      {
        "question": "アルツハイマー病の特徴はどれか",
        "answer": "大脳皮質の老人斑がみられ、初期からゲルストマン症候群や片麻痺は典型的ではない。"
      }
    ],
    "lawGroundedExplanationNotNeeded": true,
    "sourceExplanationCommonPrefix": [],
    "sourceExplanationCommonSummary": [],
    "sourceExplanationChoiceSnippets": [
      [],
      [],
      [],
      []
    ],
    "sourceExplanationChoiceCorrectness": [
      null,
      null,
      null,
      null
    ]
  },
  {
    "original_question_id": "bc0507f5c6243c95",
    "public_question_id": "bc0507f5c6243c95",
    "question_url": "https://kurohon.jp/gakusei/exams_hq/hq_20/#q77",
    "questionLabel": "問77",
    "examLabel": "第20回（2012年） 午前問題",
    "source_filepath": "output/shinkyu/questions_json/2012/00_source/question_2012_4.json",
    "explanationText": [
      "間違い。頸椎骨折だけでは症状を十分に説明できない。",
      "正しい。外傷後に両上肢のしびれと歩行障害が出るので頸髄中心性損傷が考えられる。",
      "間違い。頸髄腫瘍は急性外傷後の発症としては不自然である。",
      "間違い。腕神経叢障害では歩行障害を説明しにくい。"
    ],
    "suggestedQuestions": [
      "頸髄中心性損傷で考えられるのはどれか"
    ],
    "suggestedQuestionDetails": [
      {
        "question": "頸髄中心性損傷で考えられるのはどれか",
        "answer": "転倒後に両上肢のしびれと歩行障害がみられる症例は頸髄中心性損傷が考えられる。"
      }
    ],
    "lawGroundedExplanationNotNeeded": true,
    "sourceExplanationCommonPrefix": [],
    "sourceExplanationCommonSummary": [],
    "sourceExplanationChoiceSnippets": [
      [],
      [],
      [],
      []
    ],
    "sourceExplanationChoiceCorrectness": [
      null,
      null,
      null,
      null
    ]
  },
  {
    "original_question_id": "3299d360afd71424",
    "public_question_id": "3299d360afd71424",
    "question_url": "https://kurohon.jp/gakusei/exams_hq/hq_20/#q78",
    "questionLabel": "問78",
    "examLabel": "第20回（2012年） 午前問題",
    "source_filepath": "output/shinkyu/questions_json/2012/00_source/question_2012_4.json",
    "explanationText": [
      "間違い。横隔膜呼吸の消失は高位頸髄損傷で問題となり、この症例では典型的ではないため誤り。",
      "正しい。両上肢の脱力は頸髄中心性損傷でみられる。",
      "正しい。膝蓋腱反射亢進は脊髄障害でみられる上位運動ニューロン徴候である。",
      "正しい。排尿困難は脊髄損傷でみられる。"
    ],
    "suggestedQuestions": [
      "頸髄中心性損傷で誤っている記述はどれか"
    ],
    "suggestedQuestionDetails": [
      {
        "question": "頸髄中心性損傷で誤っている記述はどれか",
        "answer": "横隔膜呼吸の消失は高位頸髄損傷で問題となるが、この症例の典型ではない。"
      }
    ],
    "lawGroundedExplanationNotNeeded": true,
    "sourceExplanationCommonPrefix": [],
    "sourceExplanationCommonSummary": [],
    "sourceExplanationChoiceSnippets": [
      [],
      [],
      [],
      []
    ],
    "sourceExplanationChoiceCorrectness": [
      null,
      null,
      null,
      null
    ]
  },
  {
    "original_question_id": "3d658ba6fa542d69",
    "public_question_id": "3d658ba6fa542d69",
    "question_url": "https://kurohon.jp/gakusei/exams_hq/hq_20/#q79",
    "questionLabel": "問79",
    "examLabel": "第20回（2012年） 午前問題",
    "source_filepath": "output/shinkyu/questions_json/2012/00_source/question_2012_4.json",
    "explanationText": [
      "間違い。ホルター心電図は不整脈評価であり、深部静脈血栓の予測には直結しない。",
      "間違い。負荷心筋シンチグラフィは虚血性心疾患の評価である。",
      "間違い。頸動脈超音波検査は脳血管評価であり、本症の予測には用いない。",
      "正しい。下肢静脈超音波検査で深部静脈血栓を評価でき、肺塞栓症の予測に有用である。"
    ],
    "suggestedQuestions": [
      "肺塞栓症の発症予測に有用な検査はどれか"
    ],
    "suggestedQuestionDetails": [
      {
        "question": "肺塞栓症の発症予測に有用な検査はどれか",
        "answer": "下肢静脈超音波検査で深部静脈血栓を確認する。"
      }
    ],
    "lawGroundedExplanationNotNeeded": true,
    "sourceExplanationCommonPrefix": [],
    "sourceExplanationCommonSummary": [],
    "sourceExplanationChoiceSnippets": [
      [],
      [],
      [],
      []
    ],
    "sourceExplanationChoiceCorrectness": [
      null,
      null,
      null,
      null
    ]
  },
  {
    "original_question_id": "746fa1c84522e6cf",
    "public_question_id": "746fa1c84522e6cf",
    "question_url": "https://kurohon.jp/gakusei/exams_hq/hq_20/#q80",
    "questionLabel": "問80",
    "examLabel": "第20回（2012年） 午前問題",
    "source_filepath": "output/shinkyu/questions_json/2012/00_source/question_2012_4.json",
    "explanationText": [
      "正しい。脱水は血液濃縮を招き、血栓形成を助長する。",
      "間違い。貧血は主要な危険因子ではない。",
      "間違い。運動はむしろ血栓予防に働く。",
      "間違い。徐脈は本症の主要な危険因子ではない。"
    ],
    "suggestedQuestions": [
      "肺塞栓症の重要な危険因子はどれか"
    ],
    "suggestedQuestionDetails": [
      {
        "question": "肺塞栓症の重要な危険因子はどれか",
        "answer": "脱水は血液濃縮を起こし、血栓形成を助長する。"
      }
    ],
    "lawGroundedExplanationNotNeeded": true,
    "sourceExplanationCommonPrefix": [],
    "sourceExplanationCommonSummary": [],
    "sourceExplanationChoiceSnippets": [
      [],
      [],
      [],
      []
    ],
    "sourceExplanationChoiceCorrectness": [
      null,
      null,
      null,
      null
    ]
  },
  {
    "original_question_id": "81cbaf6b4f5be7ff",
    "public_question_id": "81cbaf6b4f5be7ff",
    "question_url": "https://kurohon.jp/gakusei/exams_hq/hq_20/#q81",
    "questionLabel": "問81",
    "examLabel": "第20回（2012年） 午後問題",
    "source_filepath": "output/shinkyu/questions_json/2012/00_source/question_2012_4.json",
    "explanationText": [
      "間違い。サルモネラ属の潜伏期は一週間ではなく、通常は数時間から数日である。",
      "間違い。腸炎ビブリオの食中毒はボツリヌスより頻度が高い。",
      "間違い。ボツリヌス菌毒素は加熱で不活化される。",
      "正しい。ベロ毒素で発症するのは腸管出血性大腸菌である。"
    ],
    "suggestedQuestions": [
      "細菌性食中毒で正しいのはどれか"
    ],
    "suggestedQuestionDetails": [
      {
        "question": "細菌性食中毒で正しいのはどれか",
        "answer": "ベロ毒素で発症するのは腸管出血性大腸菌である。"
      }
    ],
    "lawGroundedExplanationNotNeeded": true,
    "sourceExplanationCommonPrefix": [],
    "sourceExplanationCommonSummary": [],
    "sourceExplanationChoiceSnippets": [
      [],
      [],
      [],
      []
    ],
    "sourceExplanationChoiceCorrectness": [
      null,
      null,
      null,
      null
    ]
  },
  {
    "original_question_id": "35d1a9a8fd087da4",
    "public_question_id": "35d1a9a8fd087da4",
    "question_url": "https://kurohon.jp/gakusei/exams_hq/hq_20/#q82",
    "questionLabel": "問82",
    "examLabel": "第20回（2012年） 午後問題",
    "source_filepath": "output/shinkyu/questions_json/2012/00_source/question_2012_4.json",
    "explanationText": [
      "間違い。日和見感染は大量の抗菌薬投与だけで起こるわけではなく、免疫低下などで起こる。",
      "正しい。MRSAは院内感染の原因となる。",
      "間違い。腸管病原性大腸菌による感染症を菌交代症とはいわない。",
      "間違い。生命に対する危険度が最も高いのは1類感染症であり、5類ではない。"
    ],
    "suggestedQuestions": [
      "感染症について正しいのはどれか"
    ],
    "suggestedQuestionDetails": [
      {
        "question": "感染症について正しいのはどれか",
        "answer": "MRSAは院内感染の原因となる。"
      }
    ],
    "lawGroundedExplanationNotNeeded": true,
    "sourceExplanationCommonPrefix": [],
    "sourceExplanationCommonSummary": [],
    "sourceExplanationChoiceSnippets": [
      [],
      [],
      [],
      []
    ],
    "sourceExplanationChoiceCorrectness": [
      null,
      null,
      null,
      null
    ]
  },
  {
    "original_question_id": "3079337b942f141c",
    "public_question_id": "3079337b942f141c",
    "question_url": "https://kurohon.jp/gakusei/exams_hq/hq_20/#q83",
    "questionLabel": "問83",
    "examLabel": "第20回（2012年） 午後問題",
    "source_filepath": "output/shinkyu/questions_json/2012/00_source/question_2012_4.json",
    "explanationText": [
      "間違い。神経膠腫では難聴が初発症状となることは少ない。",
      "間違い。髄膜腫でも難聴は起こりうるが、初発症状として多いわけではない。",
      "正しい。聴神経鞘腫は難聴を初発症状としやすい。",
      "間違い。下垂体腺腫の主症状は視野障害や内分泌症状である。"
    ],
    "suggestedQuestions": [
      "難聴を初発症状とする腫瘍はどれか"
    ],
    "suggestedQuestionDetails": [
      {
        "question": "難聴を初発症状とする腫瘍はどれか",
        "answer": "聴神経鞘腫は初発症状として難聴を示しやすい。"
      }
    ],
    "lawGroundedExplanationNotNeeded": true,
    "sourceExplanationCommonPrefix": [],
    "sourceExplanationCommonSummary": [],
    "sourceExplanationChoiceSnippets": [
      [],
      [],
      [],
      []
    ],
    "sourceExplanationChoiceCorrectness": [
      null,
      null,
      null,
      null
    ]
  },
  {
    "original_question_id": "5854774a265d83a2",
    "public_question_id": "5854774a265d83a2",
    "question_url": "https://kurohon.jp/gakusei/exams_hq/hq_20/#q84",
    "questionLabel": "問84",
    "examLabel": "第20回（2012年） 午後問題",
    "source_filepath": "output/shinkyu/questions_json/2012/00_source/question_2012_4.json",
    "explanationText": [
      "間違い。じん臓機能障害は身体障害者手帳の対象である。",
      "間違い。そしゃく・嚥下機能障害も対象である。",
      "間違い。平衡機能障害も対象である。",
      "正しい。高次機能障害のみは身体障害者手帳の対象外である。"
    ],
    "suggestedQuestions": [
      "身体障害者手帳の交付対象でないのはどれか"
    ],
    "suggestedQuestionDetails": [
      {
        "question": "身体障害者手帳の交付対象でないのはどれか",
        "answer": "高次機能障害のみでは身体障害者手帳の対象にならない。"
      }
    ],
    "lawGroundedExplanationNotNeeded": true,
    "sourceExplanationCommonPrefix": [],
    "sourceExplanationCommonSummary": [],
    "sourceExplanationChoiceSnippets": [
      [],
      [],
      [],
      []
    ],
    "sourceExplanationChoiceCorrectness": [
      null,
      null,
      null,
      null
    ]
  },
  {
    "original_question_id": "51eecead98834261",
    "public_question_id": "51eecead98834261",
    "question_url": "https://kurohon.jp/gakusei/exams_hq/hq_20/#q85",
    "questionLabel": "問85",
    "examLabel": "第20回（2012年） 午後問題",
    "source_filepath": "output/shinkyu/questions_json/2012/00_source/question_2012_4.json",
    "explanationText": [
      "正しい。病棟看護師は参加する。",
      "間違い。評価会議を待ってから治療を始めるわけではない。",
      "正しい。治療経過によりゴール設定を変更する。",
      "正しい。回復期リハビリテーション病棟の症例では評価会議を行う。"
    ],
    "suggestedQuestions": [
      "回復期リハビリテーション病棟の評価会議で適切でないのはどれか"
    ],
    "suggestedQuestionDetails": [
      {
        "question": "回復期リハビリテーション病棟の評価会議で適切でないのはどれか",
        "answer": "評価会議は治療開始前に評価が完了するまで待つものではない。"
      }
    ],
    "lawGroundedExplanationNotNeeded": true,
    "sourceExplanationCommonPrefix": [],
    "sourceExplanationCommonSummary": [],
    "sourceExplanationChoiceSnippets": [
      [],
      [],
      [],
      []
    ],
    "sourceExplanationChoiceCorrectness": [
      null,
      null,
      null,
      null
    ]
  },
  {
    "original_question_id": "3ebf86cea63cfb01",
    "public_question_id": "3ebf86cea63cfb01",
    "question_url": "https://kurohon.jp/gakusei/exams_hq/hq_20/#q86",
    "questionLabel": "問86",
    "examLabel": "第20回（2012年） 午後問題",
    "source_filepath": "output/shinkyu/questions_json/2012/00_source/question_2012_4.json",
    "explanationText": [
      "正しい。6か月児ではおもちゃをつかむことができる。",
      "間違い。ビー玉をつまむのはもっと後である。",
      "間違い。手放しで立つのは1歳前後である。",
      "間違い。ひとり歩きはさらに後である。"
    ],
    "suggestedQuestions": [
      "正常な6か月児で可能な動作はどれか"
    ],
    "suggestedQuestionDetails": [
      {
        "question": "正常な6か月児で可能な動作はどれか",
        "answer": "6か月児ではおもちゃをつかむことができる。"
      }
    ],
    "lawGroundedExplanationNotNeeded": true,
    "sourceExplanationCommonPrefix": [],
    "sourceExplanationCommonSummary": [],
    "sourceExplanationChoiceSnippets": [
      [],
      [],
      [],
      []
    ],
    "sourceExplanationChoiceCorrectness": [
      null,
      null,
      null,
      null
    ]
  },
  {
    "original_question_id": "4e259f5a460054f8",
    "public_question_id": "4e259f5a460054f8",
    "question_url": "https://kurohon.jp/gakusei/exams_hq/hq_20/#q87",
    "questionLabel": "問87",
    "examLabel": "第20回（2012年） 午後問題",
    "source_filepath": "output/shinkyu/questions_json/2012/00_source/question_2012_4.json",
    "explanationText": [
      "正しい。水飲みテストは嚥下障害のスクリーニングに用いる。",
      "間違い。嚥下造影検査は精査に用いる。",
      "間違い。CRPは炎症反応の指標である。",
      "間違い。胸部X線検査はスクリーニングではない。"
    ],
    "suggestedQuestions": [
      "嚥下機能障害のスクリーニング検査はどれか"
    ],
    "suggestedQuestionDetails": [
      {
        "question": "嚥下機能障害のスクリーニング検査はどれか",
        "answer": "水飲みテストは嚥下障害のスクリーニングに用いる。"
      }
    ],
    "lawGroundedExplanationNotNeeded": true,
    "sourceExplanationCommonPrefix": [],
    "sourceExplanationCommonSummary": [],
    "sourceExplanationChoiceSnippets": [
      [],
      [],
      [],
      []
    ],
    "sourceExplanationChoiceCorrectness": [
      null,
      null,
      null,
      null
    ]
  },
  {
    "original_question_id": "9637e9692de2c8d1",
    "public_question_id": "9637e9692de2c8d1",
    "question_url": "https://kurohon.jp/gakusei/exams_hq/hq_20/#q88",
    "questionLabel": "問88",
    "examLabel": "第20回（2012年） 午後問題",
    "source_filepath": "output/shinkyu/questions_json/2012/00_source/question_2012_4.json",
    "explanationText": [
      "間違い。低周波療法の主作用は電気刺激や鎮痛で、深部加温ではない。",
      "正しい。超音波療法は深部組織への温熱効果が高い。",
      "間違い。紫外線療法は主に皮膚表層に作用する。",
      "間違い。赤外線療法は比較的浅い部位を温める。"
    ],
    "suggestedQuestions": [
      "深部組織への温熱効果が最も高い物理療法はどれか"
    ],
    "suggestedQuestionDetails": [
      {
        "question": "深部組織への温熱効果が最も高い物理療法はどれか",
        "answer": "超音波療法は深部加温に適する。"
      }
    ],
    "lawGroundedExplanationNotNeeded": true,
    "sourceExplanationCommonPrefix": [],
    "sourceExplanationCommonSummary": [],
    "sourceExplanationChoiceSnippets": [
      [],
      [],
      [],
      []
    ],
    "sourceExplanationChoiceCorrectness": [
      null,
      null,
      null,
      null
    ]
  },
  {
    "original_question_id": "9bdec2056bdfce19",
    "public_question_id": "9bdec2056bdfce19",
    "question_url": "https://kurohon.jp/gakusei/exams_hq/hq_20/#q89",
    "questionLabel": "問89",
    "examLabel": "第20回（2012年） 午後問題",
    "source_filepath": "output/shinkyu/questions_json/2012/00_source/question_2012_4.json",
    "explanationText": [
      "間違い。屈筋共同運動では肩甲帯は下制ではなく挙上・後退がみられる。",
      "間違い。肩関節は内旋ではなく外旋がみられる。",
      "正しい。屈筋共同運動では肘関節屈曲がみられる。",
      "間違い。前腕は回内ではなく回外がみられる。"
    ],
    "suggestedQuestions": [
      "上肢の屈筋共同運動で正しい組合せはどれか"
    ],
    "suggestedQuestionDetails": [
      {
        "question": "上肢の屈筋共同運動で正しい組合せはどれか",
        "answer": "屈筋共同運動では肘関節屈曲がみられる。"
      }
    ],
    "lawGroundedExplanationNotNeeded": true,
    "sourceExplanationCommonPrefix": [],
    "sourceExplanationCommonSummary": [],
    "sourceExplanationChoiceSnippets": [
      [],
      [],
      [],
      []
    ],
    "sourceExplanationChoiceCorrectness": [
      null,
      null,
      null,
      null
    ]
  },
  {
    "original_question_id": "3f3d25fa8b422af5",
    "public_question_id": "3f3d25fa8b422af5",
    "question_url": "https://kurohon.jp/gakusei/exams_hq/hq_20/#q90",
    "questionLabel": "問90",
    "examLabel": "第20回（2012年） 午後問題",
    "source_filepath": "output/shinkyu/questions_json/2012/00_source/question_2012_4.json",
    "explanationText": [
      "間違い。手指末端の壊死は肩手症候群の典型ではない。",
      "間違い。肩関節亜脱臼は肩手症候群そのものの症状ではない。",
      "間違い。手掌のしびれよりも疼痛や腫脹が目立つ。",
      "正しい。手背の腫脹は肩手症候群でみられる。"
    ],
    "suggestedQuestions": [
      "肩手症候群の症状で最も適切なのはどれか"
    ],
    "suggestedQuestionDetails": [
      {
        "question": "肩手症候群の症状で最も適切なのはどれか",
        "answer": "肩手症候群では手背の腫脹がみられる。"
      }
    ],
    "lawGroundedExplanationNotNeeded": true,
    "sourceExplanationCommonPrefix": [],
    "sourceExplanationCommonSummary": [],
    "sourceExplanationChoiceSnippets": [
      [],
      [],
      [],
      []
    ],
    "sourceExplanationChoiceCorrectness": [
      null,
      null,
      null,
      null
    ]
  },
  {
    "original_question_id": "43cc2b75ecd5e191",
    "public_question_id": "43cc2b75ecd5e191",
    "question_url": "https://kurohon.jp/gakusei/exams_hq/hq_20/#q91",
    "questionLabel": "問91",
    "examLabel": "第20回（2012年） 午後問題",
    "source_filepath": "output/shinkyu/questions_json/2012/00_source/question_2012_4.json",
    "explanationText": [
      "間違い。うつ熱への対応は解熱剤投与より環境調整が基本である。",
      "間違い。殿部褥瘡には除圧と創処置が必要で、プッシュアップは補助的である。",
      "正しい。尿路感染には間欠導尿が有用である。",
      "間違い。自律神経過反射では下肢挙上よりまず原因刺激の除去と上半身挙上が重要である。"
    ],
    "suggestedQuestions": [
      "C6レベルの脊髄損傷患者の合併症と対応の組合せで正しいのはどれか"
    ],
    "suggestedQuestionDetails": [
      {
        "question": "C6レベルの脊髄損傷患者の合併症と対応の組合せで正しいのはどれか",
        "answer": "尿路感染には間欠導尿が有用である。"
      }
    ],
    "lawGroundedExplanationNotNeeded": true,
    "sourceExplanationCommonPrefix": [],
    "sourceExplanationCommonSummary": [],
    "sourceExplanationChoiceSnippets": [
      [],
      [],
      [],
      []
    ],
    "sourceExplanationChoiceCorrectness": [
      null,
      null,
      null,
      null
    ]
  },
  {
    "original_question_id": "63c0aa7f233a1ea1",
    "public_question_id": "63c0aa7f233a1ea1",
    "question_url": "https://kurohon.jp/gakusei/exams_hq/hq_20/#q92",
    "questionLabel": "問92",
    "examLabel": "第20回（2012年） 午後問題",
    "source_filepath": "output/shinkyu/questions_json/2012/00_source/question_2012_4.json",
    "explanationText": [
      "間違い。焦－臊は五行色体の相剋関係ではない。",
      "間違い。面－唇は相剋関係ではない。",
      "間違い。憂－噦は相剋関係ではない。",
      "正しい。汗と涕は火と金に対応し、相剋関係にある。"
    ],
    "suggestedQuestions": [
      "五行色体で相剋関係にある組合せはどれか"
    ],
    "suggestedQuestionDetails": [
      {
        "question": "五行色体で相剋関係にある組合せはどれか",
        "answer": "汗は火、涕は金に属し、火は金を克する。"
      }
    ],
    "lawGroundedExplanationNotNeeded": true,
    "sourceExplanationCommonPrefix": [],
    "sourceExplanationCommonSummary": [],
    "sourceExplanationChoiceSnippets": [
      [],
      [],
      [],
      []
    ],
    "sourceExplanationChoiceCorrectness": [
      null,
      null,
      null,
      null
    ]
  },
  {
    "original_question_id": "b87ed948383b0a63",
    "public_question_id": "b87ed948383b0a63",
    "question_url": "https://kurohon.jp/gakusei/exams_hq/hq_20/#q93",
    "questionLabel": "問93",
    "examLabel": "第20回（2012年） 午後問題",
    "source_filepath": "output/shinkyu/questions_json/2012/00_source/question_2012_4.json",
    "explanationText": [
      "間違い。津液は腎と膀胱だけで生成されるわけではない。",
      "正しい。津液の代謝機構は三焦気化とされる。",
      "間違い。津液は経脈を通じて流れるわけではない。",
      "間違い。津液が停滞するのは津傷ではなく津停などと捉える。"
    ],
    "suggestedQuestions": [
      "津液について正しいのはどれか"
    ],
    "suggestedQuestionDetails": [
      {
        "question": "津液について正しいのはどれか",
        "answer": "津液の代謝は三焦の気化により行われる。"
      }
    ],
    "lawGroundedExplanationNotNeeded": true,
    "sourceExplanationCommonPrefix": [],
    "sourceExplanationCommonSummary": [],
    "sourceExplanationChoiceSnippets": [
      [],
      [],
      [],
      []
    ],
    "sourceExplanationChoiceCorrectness": [
      null,
      null,
      null,
      null
    ]
  },
  {
    "original_question_id": "3824382e6a4da513",
    "public_question_id": "3824382e6a4da513",
    "question_url": "https://kurohon.jp/gakusei/exams_hq/hq_20/#q94",
    "questionLabel": "問94",
    "examLabel": "第20回（2012年） 午後問題",
    "source_filepath": "output/shinkyu/questions_json/2012/00_source/question_2012_4.json",
    "explanationText": [
      "間違い。隠痛は陰実証よりも虚寒証や虚証でみられる所見である。",
      "間違い。潮熱は陰虚証や実熱でみられるが、陽実証の代表所見ではない。",
      "正しい。盗汗は陰虚証でみられる。",
      "間違い。拒按は実証でみられ、陽虚証ではない。"
    ],
    "suggestedQuestions": [
      "所見と病証の正しい組合せはどれか"
    ],
    "suggestedQuestionDetails": [
      {
        "question": "所見と病証の正しい組合せはどれか",
        "answer": "盗汗は陰虚証でみられる。"
      }
    ],
    "lawGroundedExplanationNotNeeded": true,
    "sourceExplanationCommonPrefix": [],
    "sourceExplanationCommonSummary": [],
    "sourceExplanationChoiceSnippets": [
      [],
      [],
      [],
      []
    ],
    "sourceExplanationChoiceCorrectness": [
      null,
      null,
      null,
      null
    ]
  },
  {
    "original_question_id": "749036b089f21702",
    "public_question_id": "749036b089f21702",
    "question_url": "https://kurohon.jp/gakusei/exams_hq/hq_20/#q95",
    "questionLabel": "問95",
    "examLabel": "第20回（2012年） 午後問題",
    "source_filepath": "output/shinkyu/questions_json/2012/00_source/question_2012_4.json",
    "explanationText": [
      "正しい。悲は五志に含まれない。",
      "間違い。恐は五志に含まれる。",
      "間違い。怒は五志に含まれる。",
      "間違い。喜は五志に含まれる。"
    ],
    "suggestedQuestions": [
      "五志に含まれないのはどれか"
    ],
    "suggestedQuestionDetails": [
      {
        "question": "五志に含まれないのはどれか",
        "answer": "悲は五志に含まれない。"
      }
    ],
    "lawGroundedExplanationNotNeeded": true,
    "sourceExplanationCommonPrefix": [],
    "sourceExplanationCommonSummary": [],
    "sourceExplanationChoiceSnippets": [
      [],
      [],
      [],
      []
    ],
    "sourceExplanationChoiceCorrectness": [
      null,
      null,
      null,
      null
    ]
  },
  {
    "original_question_id": "e49998f05ed23aed",
    "public_question_id": "e49998f05ed23aed",
    "question_url": "https://kurohon.jp/gakusei/exams_hq/hq_20/#q96",
    "questionLabel": "問96",
    "examLabel": "第20回（2012年） 午後問題",
    "source_filepath": "output/shinkyu/questions_json/2012/00_source/question_2012_4.json",
    "explanationText": [
      "正しい。食滞では食欲不振や食を嫌うことがある。",
      "正しい。食滞では呑酸がみられることがある。",
      "正しい。食滞では大便に酸臭を伴うことがある。",
      "間違い。消渇は食滞の代表的所見ではない。"
    ],
    "suggestedQuestions": [
      "食滞について誤っている記述はどれか"
    ],
    "suggestedQuestionDetails": [
      {
        "question": "食滞について誤っている記述はどれか",
        "answer": "食滞で消渇は起こらない。"
      }
    ],
    "lawGroundedExplanationNotNeeded": true,
    "sourceExplanationCommonPrefix": [],
    "sourceExplanationCommonSummary": [],
    "sourceExplanationChoiceSnippets": [
      [],
      [],
      [],
      []
    ],
    "sourceExplanationChoiceCorrectness": [
      null,
      null,
      null,
      null
    ]
  },
  {
    "original_question_id": "3c490496f5291dc4",
    "public_question_id": "3c490496f5291dc4",
    "question_url": "https://kurohon.jp/gakusei/exams_hq/hq_20/#q97",
    "questionLabel": "問97",
    "examLabel": "第20回（2012年） 午後問題",
    "source_filepath": "output/shinkyu/questions_json/2012/00_source/question_2012_4.json",
    "explanationText": [
      "間違い。太渓は腎経の経穴であり、提示された足太陰脾経の病証とは合わない。",
      "間違い。衝陽は胃経の原穴であり、症状の主経に一致しない。",
      "正しい。太白は足太陰脾経の原穴で、提示症状に合う。",
      "間違い。侠渓は胆経の経穴であり、提示された病証とは合わない。"
    ],
    "suggestedQuestions": [
      "経脈病証に用いる経穴として適切なのはどれか"
    ],
    "suggestedQuestionDetails": [
      {
        "question": "経脈病証に用いる経穴として適切なのはどれか",
        "answer": "太白は足太陰脾経の原穴で、提示症状に合う。"
      }
    ],
    "lawGroundedExplanationNotNeeded": true,
    "sourceExplanationCommonPrefix": [],
    "sourceExplanationCommonSummary": [],
    "sourceExplanationChoiceSnippets": [
      [],
      [],
      [],
      []
    ],
    "sourceExplanationChoiceCorrectness": [
      null,
      null,
      null,
      null
    ]
  },
  {
    "original_question_id": "e2ad74205ca92183",
    "public_question_id": "e2ad74205ca92183",
    "question_url": "https://kurohon.jp/gakusei/exams_hq/hq_20/#q98",
    "questionLabel": "問98",
    "examLabel": "第20回（2012年） 午後問題",
    "source_filepath": "output/shinkyu/questions_json/2012/00_source/question_2012_4.json",
    "explanationText": [
      "間違い。壮熱は高熱をいうが、一定時刻に出るとは限らない。",
      "正しい。潮熱は一定の時刻に発熱する特徴がある。",
      "間違い。但熱不寒は熱のみで寒を伴わない状態である。",
      "間違い。往来寒熱は寒熱が往来する状態である。"
    ],
    "suggestedQuestions": [
      "一定の時刻に発熱するのはどれか"
    ],
    "suggestedQuestionDetails": [
      {
        "question": "一定の時刻に発熱するのはどれか",
        "answer": "潮熱は一定の時刻に発熱する。"
      }
    ],
    "lawGroundedExplanationNotNeeded": true,
    "sourceExplanationCommonPrefix": [],
    "sourceExplanationCommonSummary": [],
    "sourceExplanationChoiceSnippets": [
      [],
      [],
      [],
      []
    ],
    "sourceExplanationChoiceCorrectness": [
      null,
      null,
      null,
      null
    ]
  },
  {
    "original_question_id": "f38782829153231d",
    "public_question_id": "f38782829153231d",
    "question_url": "https://kurohon.jp/gakusei/exams_hq/hq_20/#q99",
    "questionLabel": "問99",
    "examLabel": "第20回（2012年） 午後問題",
    "source_filepath": "output/shinkyu/questions_json/2012/00_source/question_2012_4.json",
    "explanationText": [
      "間違い。気虚証では倦怠感や自汗が中心で、本例の虚熱所見と合わない。",
      "間違い。血虚証ではめまい、動悸、顔色不華などが中心である。",
      "間違い。陽虚証では冷えや下痢が中心で、本例とは合わない。",
      "正しい。寝汗、不眠、便秘は陰虚証に合う。"
    ],
    "suggestedQuestions": [
      "この患者の病証はどれか"
    ],
    "suggestedQuestionDetails": [
      {
        "question": "この患者の病証はどれか",
        "answer": "寝汗、不眠、便秘は陰虚証に合う。"
      }
    ],
    "lawGroundedExplanationNotNeeded": true,
    "sourceExplanationCommonPrefix": [],
    "sourceExplanationCommonSummary": [],
    "sourceExplanationChoiceSnippets": [
      [],
      [],
      [],
      []
    ],
    "sourceExplanationChoiceCorrectness": [
      null,
      null,
      null,
      null
    ]
  },
  {
    "original_question_id": "e9c6a9d1b5fdb764",
    "public_question_id": "e9c6a9d1b5fdb764",
    "question_url": "https://kurohon.jp/gakusei/exams_hq/hq_20/#q100",
    "questionLabel": "問100",
    "examLabel": "第20回（2012年） 午後問題",
    "source_filepath": "output/shinkyu/questions_json/2012/00_source/question_2012_4.json",
    "explanationText": [
      "間違い。胖舌－結脈は痰湿や寒凝などでみられ、陰虚証とは合わない。",
      "間違い。痩舌－滑脈は痰湿や食滞などでみられやすい。",
      "正しい。紅舌－細脈は陰虚証に合う。",
      "間違い。淡舌－弦脈は気虚・陽虚や肝気鬱結などでみられやすい。"
    ],
    "suggestedQuestions": [
      "この患者の舌と脈の所見はどれか"
    ],
    "suggestedQuestionDetails": [
      {
        "question": "この患者の舌と脈の所見はどれか",
        "answer": "紅舌－細脈は陰虚証に合う。"
      }
    ],
    "lawGroundedExplanationNotNeeded": true,
    "sourceExplanationCommonPrefix": [],
    "sourceExplanationCommonSummary": [],
    "sourceExplanationChoiceSnippets": [
      [],
      [],
      [],
      []
    ],
    "sourceExplanationChoiceCorrectness": [
      null,
      null,
      null,
      null
    ]
  }
]
